makepip/__init__.py
makepip/__main__.py
makepip/makepip.py
makepip-0.3.dist-info/LICENCE
makepip-0.3.dist-info/METADATA
makepip-0.3.dist-info/WHEEL
makepip-0.3.dist-info/entry_points.txt
makepip-0.3.dist-info/top_level.txt
makepip-0.3.dist-info/RECORD
